traytable/__init__.py
traytable/csv.py
traytable/screens.py
traytable/wells.py
traytable-0.2.1.dist-info/LICENSE
traytable-0.2.1.dist-info/METADATA
traytable-0.2.1.dist-info/WHEEL
traytable-0.2.1.dist-info/top_level.txt
traytable-0.2.1.dist-info/RECORD
