Metadata-Version: 2.1
Name: traytable
Version: 0.2.1
Summary: A python package for tabulating crystallization results across many trays
Home-page: https://github.com/dennisbrookner/traytable
Author: Dennis Brookner
Author-email: debrookner@gmail.com
Project-URL: Bug Tracker, https://github.com/dennisbrookner/traytable/issues
Classifier: Programming Language :: Python :: 3
Classifier: License :: OSI Approved :: MIT License
Classifier: Operating System :: OS Independent
Requires-Python: >=3.6
License-File: LICENSE
Requires-Dist: pandas
Requires-Dist: numpy
Requires-Dist: varname (==0.6.4)
Provides-Extra: test
Requires-Dist: pytest ; extra == 'test'
